LICENSE
MANIFEST.in
README.md
setup.cfg
setup.py
limix_core/__init__.py
limix_core.egg-info/PKG-INFO
limix_core.egg-info/SOURCES.txt
limix_core.egg-info/dependency_links.txt
limix_core.egg-info/not-zip-safe
limix_core.egg-info/requires.txt
limix_core.egg-info/top_level.txt
limix_core/covar/__init__.py
limix_core/covar/acombinators.py
limix_core/covar/categoricalLR.py
limix_core/covar/combinators.py
limix_core/covar/cov2kronSum.py
limix_core/covar/cov2kronSumLR.py
limix_core/covar/cov3kronSumLR.py
limix_core/covar/cov_reml.py
limix_core/covar/covar_base.py
limix_core/covar/diagonal.py
limix_core/covar/dirIndirCov.py
limix_core/covar/fixed.py
limix_core/covar/freeform.py
limix_core/covar/kronecker.py
limix_core/covar/lowrank.py
limix_core/covar/sqexp.py
limix_core/covar/zkz.py
limix_core/covar/test/test_combinators.py
limix_core/covar/test/test_cov2kronSum.py
limix_core/covar/test/test_cov2kronSumLR.py
limix_core/covar/test/test_cov3kronSumLR.py
limix_core/covar/test/test_dirIndirCov.py
limix_core/covar/test/test_fixed.py
limix_core/covar/test/test_freeform.py
limix_core/covar/test/test_kronecker.py
limix_core/covar/test/test_lowrank.py
limix_core/covar/test/test_sqexp.py
limix_core/covar/util/__init__.py
limix_core/gp/__init__.py
limix_core/gp/gp2kronSum.py
limix_core/gp/gp2kronSumLR.py
limix_core/gp/gp3kronSumLR.py
limix_core/gp/gp_base.py
limix_core/gp/relay.py
limix_core/hcache/__init__.py
limix_core/hcache/_hcache.py
limix_core/likelihood/__init__.py
limix_core/likelihood/likelihood_base.py
limix_core/linalg/__init__.py
limix_core/linalg/dist.py
limix_core/linalg/linalg_matrix.py
limix_core/mean/__init__.py
limix_core/mean/base.py
limix_core/mean/linear.py
limix_core/mean/mean.py
limix_core/mean/meanKronSum.py
limix_core/mean/mean_base.py
limix_core/mean/mean_efficient.py
limix_core/mean/tests/test_mean.py
limix_core/optimize/__init__.py
limix_core/optimize/optimize_bfgs.py
limix_core/test/test_gp2kronSum.py
limix_core/test/test_gp2kronSumLR.py
limix_core/test/test_gp3kronSumLR.py
limix_core/test/test_gp_base.py
limix_core/test/test_gp_more.py
limix_core/type/__init__.py
limix_core/type/exception.py
limix_core/type/observed.py
limix_core/util/__init__.py
