Metadata-Version: 1.1
Name: limix-core
Version: 1.0.1
Summary: Fast inference for Linear Mixed Models.
Home-page: https://github.com/limix/limix-core
Author: Limix Developers
Author-email: horta@ebi.ac.uk
License: Apache License 2.0'
Platform: UNKNOWN
Classifier: Development Status :: 5 - Production/Stable
Classifier: License :: OSI Approved :: MIT License
Classifier: Operating System :: OS Independent
